mkdocs_onecompiler_plugin/__init__.py
mkdocs_onecompiler_plugin/main.py
mkdocs_onecompiler_plugin/schema.py
mkdocs_onecompiler_plugin-0.1.0.dist-info/LICENSE
mkdocs_onecompiler_plugin-0.1.0.dist-info/METADATA
mkdocs_onecompiler_plugin-0.1.0.dist-info/WHEEL
mkdocs_onecompiler_plugin-0.1.0.dist-info/RECORD
