Metadata-Version: 2.1
Name: mkdocs-onecompiler-plugin
Version: 0.1.0
Summary: Include OneCompiler online compiler to your mkdocs website
Author: Alban Siffer
Author-email: alban.siffer@irisa.fr
Requires-Python: >=3.11,<4.0
Classifier: Programming Language :: Python :: 3
Classifier: Programming Language :: Python :: 3.11
Requires-Dist: mkdocs (>=1.5.1,<2.0.0)
Requires-Dist: mkdocs-material (>=9.1.21,<10.0.0)
Requires-Dist: pydantic (>=2.1.1,<3.0.0)
